orange_starfrac/CompletionInput.py
orange_starfrac/CompletionOutput.py
orange_starfrac/FracturesInput.py
orange_starfrac/FracturesOutput.py
orange_starfrac/InputMixin.py
orange_starfrac/PseudoPointsInput.py
orange_starfrac/PseudoPointsOutput.py
orange_starfrac/RpcClient.py
orange_starfrac/WellAttributesInput.py
orange_starfrac/WellAttributesOutput.py
orange_starfrac/__init__.py
orange_starfrac/utils.py
orange_starfrac/icons/completionInput.svg
orange_starfrac/icons/completionOutput.svg
orange_starfrac/icons/fracturesInput.svg
orange_starfrac/icons/fracturesOutput.svg
orange_starfrac/icons/input.svg
orange_starfrac/icons/mvaPointsInput.svg
orange_starfrac/icons/mvaPointsOutput.svg
orange_starfrac/icons/vectorpaint.svg
orange_starfrac/icons/wellAttributesInput.svg
orange_starfrac/icons/wellAttributesOutput.svg
orange_starfrac-1.0.2.dist-info/METADATA
orange_starfrac-1.0.2.dist-info/WHEEL
orange_starfrac-1.0.2.dist-info/entry_points.txt
orange_starfrac-1.0.2.dist-info/top_level.txt
orange_starfrac-1.0.2.dist-info/RECORD
