Metadata-Version: 2.1
Name: orange-starfrac
Version: 1.0.2
Summary: Orange widgets for interaction with StarFrac
Home-page: UNKNOWN
Author: Rogii Inc.
Author-email: UNKNOWN
License: UNKNOWN
Platform: UNKNOWN
Classifier: Programming Language :: Python :: 3
Classifier: Operating System :: OS Independent
Requires-Dist: zerorpc
